proplogic/__init__.py
proplogic/logic_ast.py
proplogic/logic_parser.py
proplogic/logic_tokenizer.py
proplogic/logic_visualizer.py
proplogic/truth_value_assignment.py
proplogic-0.0.3.dist-info/LICENSE
proplogic-0.0.3.dist-info/METADATA
proplogic-0.0.3.dist-info/WHEEL
proplogic-0.0.3.dist-info/top_level.txt
proplogic-0.0.3.dist-info/RECORD
