Metadata-Version: 2.1
Name: proplogic
Version: 0.0.3
Summary: A simple propositional logic parser and visualizer
Home-page: https://github.com/ryoryon66/propositional_logic_expr_parser
Author: ryoryon66
License: MIT
Platform: UNKNOWN
License-File: LICENSE
Requires-Dist: networkx (==3.0)
Requires-Dist: pygraphviz (==1.10)
Requires-Dist: pytest (==7.2.2)
